octoflow_plugins/__init__.py
octoflow_plugins/tracking/__init__.py
octoflow_plugins/tracking/artifacts/__init__.py
octoflow_plugins/tracking/artifacts/json_handler.py
octoflow_plugins/tracking/artifacts/pandas_handler.py
octoflow_plugins/tracking/artifacts/pickle_handler.py
octoflow_plugins/tracking/artifacts/safetensors_handler.py
octoflow_plugins/tracking/artifacts/torch_handler.py
octoflow_plugins/tracking/artifacts/transformers_handler.py
octoflow_plugins-0.0.5.dist-info/METADATA
octoflow_plugins-0.0.5.dist-info/WHEEL
octoflow_plugins-0.0.5.dist-info/licenses/LICENSE
octoflow_plugins-0.0.5.dist-info/RECORD
